dkextract/__init__.py
dkextract/dkextract.py
dkextract-1.49.dist-info/LICENSE
dkextract-1.49.dist-info/METADATA
dkextract-1.49.dist-info/WHEEL
dkextract-1.49.dist-info/top_level.txt
dkextract-1.49.dist-info/RECORD
