Metadata-Version: 2.1
Name: dkextract
Version: 1.49
Summary: A tool to get certain data from DraftKings
Home-page: https://github.com/climardo/dkextract
Author: Carlos Limardo
Author-email: Carlos Limardo <climardo@gmail.com>
License: GNU GENERAL PUBLIC LICENSE
Project-URL: Homepage, https://github.com/climardo/dkextract
Project-URL: Bug Tracker, https://github.com/climardo/dkextract/issues
Classifier: Programming Language :: Python :: 3
Classifier: License :: OSI Approved :: MIT License
Classifier: Operating System :: OS Independent
Requires-Python: >=3.7.3
License-File: LICENSE
Requires-Dist: requests
Requires-Dist: python-dateutil
Requires-Dist: lxml
